setup.py
bin/check_smoker_plugin.py
bin/smokercli.py
bin/smokerd.py
gdc_smoker.egg-info/PKG-INFO
gdc_smoker.egg-info/SOURCES.txt
gdc_smoker.egg-info/dependency_links.txt
gdc_smoker.egg-info/pbr.json
gdc_smoker.egg-info/requires.txt
gdc_smoker.egg-info/top_level.txt
smoker/DESCRIPTION.md
smoker/__init__.py
smoker/client/__init__.py
smoker/client/cli.py
smoker/client/out_junit/__init__.py
smoker/client/out_junit/default_config.py
smoker/client/out_junit/rows.py
smoker/client/out_junit/xml_builder.py
smoker/client/plugins/__init__.py
smoker/logger/__init__.py
smoker/logger/level_handler.py
smoker/server/__init__.py
smoker/server/daemon.py
smoker/server/exceptions.py
smoker/server/parser.py
smoker/server/restserver.py
smoker/server/plugins/__init__.py
smoker/server/plugins/fsmount.py
smoker/server/plugins/glusterfs.py
smoker/server/plugins/mongo.py
smoker/server/plugins/testconnection.py
smoker/server/plugins/uname.py
smoker/server/plugins/varnishparser.py
smoker/util/__init__.py
smoker/util/command.py
smoker/util/console.py
smoker/util/nagios.py
smoker/util/progressbar.py
smoker/util/tap.py