Metadata-Version: 1.1
Name: gdc-smoker
Version: 2.0.11
Summary: Smoke Testing Framework
Home-page: https://github.com/gooddata/smoker
Author: Filip Pytloun
Author-email: filip@pytloun.cz
License: BSD
Download-URL: https://github.com/gooddata/smoker
Platform: POSIX
Classifier: Development Status :: 5 - Production/Stable
Classifier: Environment :: Console
Classifier: Environment :: No Input/Output (Daemon)
Classifier: Intended Audience :: Developers
Classifier: Intended Audience :: System Administrators
Classifier: License :: OSI Approved :: BSD License
Classifier: Natural Language :: English
Classifier: Operating System :: POSIX
Classifier: Programming Language :: Python
Classifier: Programming Language :: Python :: Implementation :: CPython
Classifier: Topic :: Software Development :: Testing
Classifier: Topic :: System :: Monitoring
Provides: smoker
